README.rst
setup.py
Anemone.egg-info/PKG-INFO
Anemone.egg-info/SOURCES.txt
Anemone.egg-info/dependency_links.txt
Anemone.egg-info/requires.txt
Anemone.egg-info/top_level.txt
anemone/__init__.py
anemone/__main__.py
anemone/gui_wx.py
anemone/reporter.py