Metadata-Version: 1.1
Name: Anemone
Version: 0.0.1
Summary: Monitor long running analyses by remote plotting of selected variables
Home-page: https://bitbucket.org/trlandet/anemone
Author: Tormod Landet
Author-email: UNKNOWN
License: UNKNOWN
Platform: UNKNOWN
Classifier: Development Status :: 3 - Alpha
Classifier: Intended Audience :: Science/Research
Classifier: License :: OSI Approved :: Apache Software License
Classifier: Operating System :: OS Independent
Classifier: Programming Language :: Python :: 2.7
Classifier: Topic :: Scientific/Engineering :: Visualization
Classifier: Topic :: Software Development :: Libraries :: Python Modules
